wifibackup/__init__.py
wifibackup/wifi.py
wifi_backup-0.0.4.dist-info/METADATA
wifi_backup-0.0.4.dist-info/WHEEL
wifi_backup-0.0.4.dist-info/entry_points.txt
wifi_backup-0.0.4.dist-info/top_level.txt
wifi_backup-0.0.4.dist-info/RECORD
